meta_eukaryome_detect/__init__.py
meta_eukaryome_detect/create_ngless_template.py
meta_eukaryome_detect/depth_summary.py
meta_eukaryome_detect/external_tools.py
meta_eukaryome_detect/meta_eukaryome_database.py
meta_eukaryome_detect/meta_eukaryome_detect.py
meta_eukaryome_detect-0.1.1.dist-info/LICENSE
meta_eukaryome_detect-0.1.1.dist-info/METADATA
meta_eukaryome_detect-0.1.1.dist-info/WHEEL
meta_eukaryome_detect-0.1.1.dist-info/entry_points.txt
meta_eukaryome_detect-0.1.1.dist-info/RECORD
