Metadata-Version: 2.1
Name: meta_eukaryome_detect
Version: 0.1.1
Summary: Pathogen, Parasite, Eukaryote and Virus detection in metagenomes..
Home-page: https://github.com/grp-bork/meta_eukaryome_detect
License: MIT
Author: Anthony Fullam
Author-email: anthony.fullam@embl.de
Requires-Python: >=3.11,<4.0
Classifier: Development Status :: 2 - Pre-Alpha
Classifier: Intended Audience :: Developers
Classifier: License :: OSI Approved :: MIT License
Classifier: Natural Language :: English
Classifier: Programming Language :: Python :: 3
Classifier: Programming Language :: Python :: 3.11
Classifier: Programming Language :: Python :: 3.12
Provides-Extra: dev
Provides-Extra: doc
Provides-Extra: test
Requires-Dist: black (>=23.10.1,<24.0.0) ; extra == "test"
Requires-Dist: bump2version (>=1.0.1,<2.0.0) ; extra == "dev"
Requires-Dist: flake8 (>=3.9.2,<4.0.0) ; extra == "test"
Requires-Dist: flake8-docstrings (>=1.6.0,<2.0.0) ; extra == "test"
Requires-Dist: flask (>=3.0.0,<4.0.0)
Requires-Dist: isort (>=5.8.0,<6.0.0) ; extra == "test"
Requires-Dist: jinja2 (>=3.1.2,<4.0.0)
Requires-Dist: mkdocs (>=1.5.3,<2.0.0) ; extra == "doc"
Requires-Dist: mkdocs-autorefs (>=0.5.0,<0.6.0) ; extra == "doc"
Requires-Dist: mkdocs-include-markdown-plugin (>=6.0.3,<7.0.0) ; extra == "doc"
Requires-Dist: mkdocs-material (>=6.1.7,<7.0.0) ; extra == "doc"
Requires-Dist: mkdocs-material-extensions (>=1.0.1,<2.0.0)
Requires-Dist: mkdocstrings (>=0.23.0,<0.24.0) ; extra == "doc"
Requires-Dist: mkdocstrings-python (>=1.7.3,<2.0.0)
Requires-Dist: mypy (>=0.900,<0.901) ; extra == "test"
Requires-Dist: pandas (>=2.2.3,<3.0.0)
Requires-Dist: pip (>=20.3.1,<21.0.0) ; extra == "dev"
Requires-Dist: pre-commit (>=2.12.0,<3.0.0) ; extra == "dev"
Requires-Dist: pytest (>=6.2.4,<7.0.0) ; extra == "test"
Requires-Dist: pytest-cov (>=2.12.0,<3.0.0) ; extra == "test"
Requires-Dist: requests (>=2.31.0,<3.0.0)
Requires-Dist: toml (>=0.10.2,<0.11.0) ; extra == "dev"
Requires-Dist: tox (>=3.20.1,<4.0.0) ; extra == "dev"
Requires-Dist: twine (>=3.3.0,<4.0.0) ; extra == "dev"
Requires-Dist: types-requests (>=2.31.0.10,<3.0.0.0)
Requires-Dist: virtualenv (>=20.2.2,<21.0.0) ; extra == "dev"
